qdls/__init__.py
qdls/cli.py
qdls/data.py
qdls/losses.py
qdls/metrics.py
qdls/tensor_ops.py
qdls/utils.py
qdls/code_template/README.md
qdls/code_template/notebooks/statis.ipynb
qdls/code_template/preliminary/example.py
qdls/code_template/src/frame.py
qdls/code_template/src/main.py
qdls/code_template/src/pl_callbacks.py
qdls/code_template/src/utils.py
qdls/code_template/src/configs/example.yaml
qdls/code_template/src/data_utils/__init__.py
qdls/code_template/src/data_utils/common.py
qdls/code_template/src/models/__init__.py
qdls/custom/__init__.py
qdls/custom/qwen_char_tokenizer.py
qdls/deprecate/__init__.py
qdls/deprecate/data.py
qdls/deprecate/loggers.py
qdls/deprecate/object.py
qdls/deprecate/optim.py
qdls/deprecate/pretrains.py
qdls/deprecate/test.py
qdls/deprecate/train.py
qdls/draw/__init__.py
qdls/draw/experiment.py
qdls/draw/stats.py
qdls/gql/__init__.py
qdls/gql/process_utils.py
qdls/gql/utils.py
qdls/gql/cypher/__init__.py
qdls/gql/cypher/grammar/Cypher.interp
qdls/gql/cypher/grammar/Cypher.tokens
qdls/gql/cypher/grammar/CypherLexer.interp
qdls/gql/cypher/grammar/CypherLexer.py
qdls/gql/cypher/grammar/CypherLexer.tokens
qdls/gql/cypher/grammar/CypherListener.py
qdls/gql/cypher/grammar/CypherParser.py
qdls/gql/cypher/grammar/CypherVisitor.py
qdls/gql/cypher/grammar/__init__.py
qdls/gql/cypher/utils/__init__.py
qdls/gql/cypher/utils/execute.py
qdls/gql/cypher/utils/kqa_eval.py
qdls/gql/cypher/utils/parse.py
qdls/gql/cypher/utils/syntax.py
qdls/gql/sparql/__init__.py
qdls/gql/sparql/grammar/Sparql.interp
qdls/gql/sparql/grammar/Sparql.tokens
qdls/gql/sparql/grammar/SparqlLexer.interp
qdls/gql/sparql/grammar/SparqlLexer.py
qdls/gql/sparql/grammar/SparqlLexer.tokens
qdls/gql/sparql/grammar/SparqlListener.py
qdls/gql/sparql/grammar/SparqlParser.py
qdls/gql/sparql/grammar/SparqlVisitor.py
qdls/gql/sparql/grammar/__init__.py
qdls/gql/sparql/utils/__init__.py
qdls/gql/sparql/utils/kqa_eval.py
qdls/gql/sparql/utils/parse.py
qdls/gql/sparql/utils/syntax.py
qdls-0.1.17.dist-info/METADATA
qdls-0.1.17.dist-info/WHEEL
qdls-0.1.17.dist-info/entry_points.txt
qdls-0.1.17.dist-info/licenses/LICENSE
qdls-0.1.17.dist-info/RECORD
