Metadata-Version: 2.4
Name: qdls
Version: 0.1.17
Summary: Q-Deep Learning Snippets, my working code snippets
Project-URL: Homepage, https://github.com/Qing25/qdls
Author-email: Qing25 <aqsz2526@outlook.com>
License-File: LICENSE
Classifier: License :: OSI Approved :: MIT License
Classifier: Operating System :: OS Independent
Classifier: Programming Language :: Python :: 3
Requires-Python: >=3.8
Requires-Dist: fire
Requires-Dist: loguru
Requires-Dist: omegaconf
Requires-Dist: termcolor
Requires-Dist: tqdm
